gym_collision_avoidance/__init__.py
gym_collision_avoidance/envs/Map.py
gym_collision_avoidance/envs/__init__.py
gym_collision_avoidance/envs/agent.py
gym_collision_avoidance/envs/collision_avoidance_env.py
gym_collision_avoidance/envs/config.py
gym_collision_avoidance/envs/test_cases.py
gym_collision_avoidance/envs/util.py
gym_collision_avoidance/envs/vec_env.py
gym_collision_avoidance/envs/visualize.py
gym_collision_avoidance/envs/wrappers.py
gym_collision_avoidance/envs/dynamics/Dynamics.py
gym_collision_avoidance/envs/dynamics/ExternalDynamics.py
gym_collision_avoidance/envs/dynamics/UnicycleDynamics.py
gym_collision_avoidance/envs/dynamics/UnicycleDynamicsMaxTurnRate.py
gym_collision_avoidance/envs/dynamics/__init__.py
gym_collision_avoidance/envs/policies/CADRLPolicy.py
gym_collision_avoidance/envs/policies/CARRLPolicy.py
gym_collision_avoidance/envs/policies/DRLLongPolicy.py
gym_collision_avoidance/envs/policies/ExternalPolicy.py
gym_collision_avoidance/envs/policies/GA3CCADRLPolicy.py
gym_collision_avoidance/envs/policies/InternalPolicy.py
gym_collision_avoidance/envs/policies/LearningPolicy.py
gym_collision_avoidance/envs/policies/LearningPolicyGA3C.py
gym_collision_avoidance/envs/policies/NonCooperativePolicy.py
gym_collision_avoidance/envs/policies/PPOCADRLPolicy.py
gym_collision_avoidance/envs/policies/Policy.py
gym_collision_avoidance/envs/policies/RVOPolicy.py
gym_collision_avoidance/envs/policies/StaticPolicy.py
gym_collision_avoidance/envs/policies/__init__.py
gym_collision_avoidance/envs/policies/CADRL/__init__.py
gym_collision_avoidance/envs/policies/CADRL/pickle_files/__init__.py
gym_collision_avoidance/envs/policies/CADRL/pickle_files/multi/__init__.py
gym_collision_avoidance/envs/policies/CADRL/pickle_files/multi/nn_rl_training_param.p
gym_collision_avoidance/envs/policies/CADRL/pickle_files/multi/nn_training_param.p
gym_collision_avoidance/envs/policies/CADRL/pickle_files/multi/no_constr_none/RL_selfplay/4_agents_policy_iter_1000.p
gym_collision_avoidance-0.0.3.dist-info/LICENSE
gym_collision_avoidance-0.0.3.dist-info/METADATA
gym_collision_avoidance-0.0.3.dist-info/WHEEL
gym_collision_avoidance-0.0.3.dist-info/top_level.txt
gym_collision_avoidance-0.0.3.dist-info/RECORD
