Metadata-Version: 2.1
Name: gym-collision-avoidance
Version: 0.0.3
Summary: Simulation environment for collision avoidance
Home-page: https://github.com/mit-acl/gym-collision-avoidance
Author: Michael Everett, Yu Fan Chen, Jonathan P. How, MIT
Keywords: robotics planning gym rl
License-File: LICENSE
Requires-Dist: tensorflow
Requires-Dist: Pillow
Requires-Dist: PyOpenGL
Requires-Dist: pyyaml
Requires-Dist: matplotlib
Requires-Dist: pytz
Requires-Dist: imageio (==2.4.1)
Requires-Dist: gym
Requires-Dist: moviepy
Requires-Dist: pandas
